README.md
setup.cfg
setup.py
sqldiff/__init__.py
sqldiff/utils.py
sqldiff.egg-info/PKG-INFO
sqldiff.egg-info/SOURCES.txt
sqldiff.egg-info/dependency_links.txt
sqldiff.egg-info/requires.txt
sqldiff.egg-info/top_level.txt
sqldiff/comp/__init__.py
sqldiff/comp/compare.py
sqldiff/comp/syntax_analysis.py
sqldiff/meta/__init__.py
sqldiff/meta/column_description.py
sqldiff/meta/dbsystem.py
sqldiff/meta/meta_connection_dispatcher.py
sqldiff/meta/postgres_meta.py
sqldiff/meta/teradata_meta.py
sqldiff/relation/__init__.py
sqldiff/relation/relation_manager.py
sqldiff/relation/relation_register.py
tests/__init__.py
tests/test_compare.py
tests/test_relation_manager.py
tests/test_syntax_analysis.py