Metadata-Version: 1.1
Name: sqldiff
Version: 0.0.4
Summary: Compare sql objects structure (tables, views or queries) on different databases
Home-page: https://github.com/m-matelski/sqldiff
Author: Mateusz Matelski
Author-email: m.z.matelski@gmail.com
License: MIT
Download-URL: https://github.com/m-matelski/sqldiff/archive/v0.0.4.tar.gz
Keywords: sql,diff,postgres,teradata
Platform: UNKNOWN
Classifier: Development Status :: 3 - Alpha
Classifier: Intended Audience :: Developers
Classifier: Topic :: Software Development :: Build Tools
Classifier: License :: OSI Approved :: MIT License
Classifier: Programming Language :: Python :: 3.8
